vpt_plugin_cellpose/__init__.py
vpt_plugin_cellpose/predict.py
vpt_plugin_cellpose/segment.py
vpt_plugin_cellpose-1.0.2.dist-info/LICENSE.md
vpt_plugin_cellpose-1.0.2.dist-info/METADATA
vpt_plugin_cellpose-1.0.2.dist-info/WHEEL
vpt_plugin_cellpose-1.0.2.dist-info/RECORD
