Metadata-Version: 2.1
Name: vpt_plugin_cellpose
Version: 1.0.2
Summary: Cellpose Plugin for VPT
Home-page: https://github.com/Vizgen/vizgen-postprocessing
License: Apache-2.0
Author: Vizgen
Author-email: techsupport@vizgen.com
Maintainer: Timothy Wiggin
Maintainer-email: timothy.wiggin@vizgen.com
Requires-Python: >=3.9,<3.11
Classifier: Development Status :: 5 - Production/Stable
Classifier: License :: OSI Approved :: Apache Software License
Classifier: Natural Language :: English
Classifier: Operating System :: MacOS :: MacOS X
Classifier: Operating System :: Microsoft :: Windows
Classifier: Operating System :: POSIX :: Linux
Classifier: Programming Language :: Python :: 3
Classifier: Programming Language :: Python :: 3.9
Classifier: Programming Language :: Python :: 3.10
Classifier: Topic :: Scientific/Engineering :: Bio-Informatics
Classifier: Topic :: Scientific/Engineering :: Image Processing
Requires-Dist: cellpose (==1.0.2)
Requires-Dist: numba (>=0.55.2)
Requires-Dist: numpy (>=1.24.3)
Requires-Dist: pandas (>=2.0.3)
Requires-Dist: torch (>=2.0.0,!=2.0.1,!=2.1.0)
Requires-Dist: vpt_core (>=1.1.0)
Project-URL: Documentation, https://vizgen.github.io/vizgen-postprocessing/
Project-URL: Repository, https://github.com/Vizgen/vizgen-postprocessing
